easy_zoom/__init__.py
easy_zoom/client.py
zoom_client/__init__.py
zoom_client/cleint.py
zoom_client/client.py
EasyZoom-1.0.3.dist-info/METADATA
EasyZoom-1.0.3.dist-info/WHEEL
EasyZoom-1.0.3.dist-info/top_level.txt
EasyZoom-1.0.3.dist-info/RECORD
