Metadata-Version: 2.1
Name: EasyZoom
Version: 1.0.3
Summary: A python zoom client for generating links using python
Home-page: https://github.com/Kaleb-Abiy/EasyZoom
Author: Kaleb Abiy
Author-email: kalebabiy2012@gmail.com
License: MIT
Keywords: Python,Zoom,Meeting,Link,Meeting Link
Platform: UNKNOWN
Classifier: Development Status :: 3 - Alpha
Classifier: License :: OSI Approved :: MIT License
Classifier: Programming Language :: Python :: 3
Classifier: Programming Language :: Python :: 3.8
Classifier: Programming Language :: Python :: 3.9
Requires-Python: >=3.8
